Metadata-Version: 2.1
Name: square-pass
Version: 0.0.2
Summary: CLI Based Password Manager
Home-page: https://github.com/jis4nx/square-pass
Author: Rakibul Islam Jisan
Author-email: jis4nx@gmail.com
Project-URL: Bug Reports, https://github.com/jis4nx/square-pass/issues
Project-URL: Funding, https://donate.pypi.org
Project-URL: Source, https://github.com/jis4nx/square-pass/
Keywords: password_manager,encryption,aes256,cli-password-manager
Classifier: Development Status :: 5 - Production/Stable
Classifier: Intended Audience :: Developers
Classifier: Topic :: Software Development :: Build Tools
Classifier: License :: OSI Approved :: MIT License
Classifier: Programming Language :: Python :: 3.6
Classifier: Programming Language :: Python :: 3.7
Classifier: Programming Language :: Python :: 3.8
Classifier: Programming Language :: Python :: 3.9
Classifier: Programming Language :: Python :: 3.10
Classifier: Programming Language :: Python :: 3.11
Classifier: Programming Language :: Python :: 3 :: Only
Requires-Python: >=3.6, <3.12
License-File: LICENSE
Requires-Dist: pycryptodome ==3.10.1
Requires-Dist: prettytable ==2.4.0
Requires-Dist: rich ==10.15.2
Requires-Dist: pyperclip
Requires-Dist: psutil
Requires-Dist: setuptools
Requires-Dist: wheel
Requires-Dist: PyYAML
